upstash_redis/__init__.py
upstash_redis/asyncio/__init__.py
upstash_redis/asyncio/client.py
upstash_redis/client.py
upstash_redis/commands/__init__.py
upstash_redis/commands/async_commands.py
upstash_redis/commands/async_commands.pyi
upstash_redis/commands/commands.py
upstash_redis/commands/commands.pyi
upstash_redis/config.py
upstash_redis/exception.py
upstash_redis/http.py
upstash_redis/schema/commands/parameters.py
upstash_redis/schema/http.py
upstash_redis/typing.py
upstash_redis/utils/base.py
upstash_redis/utils/comparison.py
upstash_redis/utils/exception.py
upstash_redis/utils/format.py
upstash_redis-0.14.5.dist-info/LICENSE
upstash_redis-0.14.5.dist-info/METADATA
upstash_redis-0.14.5.dist-info/WHEEL
upstash_redis-0.14.5.dist-info/RECORD
