Metadata-Version: 2.1
Name: upstash-redis
Version: 0.14.5
Summary: Serverless Redis Sdk from Upstash
Author: Upstash
Author-email: support@upstash.com
Requires-Python: >=3.8,<4.0
Classifier: Programming Language :: Python :: 3
Classifier: Programming Language :: Python :: 3.8
Classifier: Programming Language :: Python :: 3.9
Classifier: Programming Language :: Python :: 3.10
Classifier: Programming Language :: Python :: 3.11
Requires-Dist: aiohttp (>=3.8.4,<4.0.0)
Requires-Dist: pytest (>=7.3.0,<8.0.0)
Requires-Dist: pytest-asyncio (>=0.21.0,<0.22.0)
Requires-Dist: requests (>=2.31.0,<3.0.0)
Requires-Dist: urllib3 (>=1.26.6,<2.0)
